compute_horde_facilitator_sdk-0.0.7.dist-info/METADATA
compute_horde_facilitator_sdk-0.0.7.dist-info/WHEEL
compute_horde_facilitator_sdk-0.0.7.dist-info/entry_points.txt
compute_horde_facilitator_sdk-0.0.7.dist-info/licenses/LICENSE
compute_horde_facilitator_sdk/__init__.py
compute_horde_facilitator_sdk/_internal/__init__.py
compute_horde_facilitator_sdk/_internal/api_models.py
compute_horde_facilitator_sdk/_internal/exceptions.py
compute_horde_facilitator_sdk/_internal/sdk.py
compute_horde_facilitator_sdk/py.typed
compute_horde_facilitator_sdk/v1.py
compute_horde_facilitator_sdk-0.0.7.dist-info/RECORD
