Metadata-Version: 2.1
Name: compute-horde-facilitator-sdk
Version: 0.0.7
Summary: SDK library to communicate with ComputeHorde Facilitator
Author: Backend Developers LTD
License: MIT
Classifier: Development Status :: 2 - Pre-Alpha
Classifier: Intended Audience :: Developers
Classifier: Topic :: Software Development :: Libraries
Classifier: License :: OSI Approved :: MIT License
Classifier: Programming Language :: Python :: 3
Classifier: Programming Language :: Python :: 3.11
Project-URL: Source, https://github.com/backend-developers-ltd/compute-horde-facilitator-sdk
Project-URL: Issue Tracker, https://github.com/backend-developers-ltd/compute-horde-facilitator-sdk/issues
Requires-Python: ==3.11.*
Requires-Dist: annotated_types>=0.5.0
Requires-Dist: httpx>=0.27.0
Requires-Dist: phx-class-registry>=4.1.0
Requires-Dist: typing_extensions
Requires-Dist: compute-horde>=0.0.20
